stlog_fastapi_middlewares/__init__.py
stlog_fastapi_middlewares/access_log.py
stlog_fastapi_middlewares/context.py
stlog_fastapi_middlewares/exception.py
stlog_fastapi_middlewares-0.2.1.dist-info/licenses/LICENSE
stlog_fastapi_middlewares-0.2.1.dist-info/METADATA
stlog_fastapi_middlewares-0.2.1.dist-info/WHEEL
stlog_fastapi_middlewares-0.2.1.dist-info/top_level.txt
stlog_fastapi_middlewares-0.2.1.dist-info/RECORD
