Metadata-Version: 2.4
Name: stlog-fastapi-middlewares
Version: 0.2.1
Summary: FastAPI middlewares to improve logging with stlog library
Requires-Python: >=3.10
License-File: LICENSE
Requires-Dist: starlette>=0.46.2
Requires-Dist: stlog>=0.4.3
Dynamic: license-file
